leglight/__init__.py
leglight/__version__.py
leglight/discovery.py
leglight/leglight.py
leglight-0.2.0.dist-info/LICENSE
leglight-0.2.0.dist-info/METADATA
leglight-0.2.0.dist-info/WHEEL
leglight-0.2.0.dist-info/top_level.txt
leglight-0.2.0.dist-info/RECORD
