Metadata-Version: 2.1
Name: leglight
Version: 0.2.0
Summary: A Python module designed to control the Elgato brand Lights.
Home-page: https://gitlab.com/obviate.io/pyleglight
Author: Jon Davis / Obviate.io
Author-email: python-code@obviate.io
License: UNKNOWN
Keywords: elgato,key light,corsair
Platform: unix
Platform: linux
Platform: osx
Classifier: Programming Language :: Python :: 3
Classifier: License :: OSI Approved :: MIT License
Classifier: Operating System :: OS Independent
Classifier: Development Status :: 3 - Alpha
Classifier: Topic :: Software Development :: Libraries :: Python Modules
Classifier: Operating System :: POSIX
Classifier: Operating System :: POSIX :: Linux
Classifier: Operating System :: MacOS :: MacOS X
Requires-Python: >=3.6
Requires-Dist: zeroconf (>=0.24.3)
Requires-Dist: requests (>=2.22.0)
